oxford/AsyncClient.py
oxford/Exceptions.py
oxford/SyncClient.py
oxford/__init__.py
Oxford.py_Rewrite-1.0.1.dist-info/LICENSE
Oxford.py_Rewrite-1.0.1.dist-info/METADATA
Oxford.py_Rewrite-1.0.1.dist-info/WHEEL
Oxford.py_Rewrite-1.0.1.dist-info/top_level.txt
Oxford.py_Rewrite-1.0.1.dist-info/RECORD
