Metadata-Version: 2.1
Name: Oxford.py-Rewrite
Version: 1.0.1
Summary: Oxford API wrapper
Home-page: https://github.com/PixelAgent007/Oxford.py
Author-email: hello@oskar.global
License: UNKNOWN
Project-URL: Bug Tracker, https://github.com/PixelAgent007/Oxford.py/issues
Platform: UNKNOWN
Classifier: Programming Language :: Python :: 3
Classifier: License :: OSI Approved :: MIT License
Classifier: Operating System :: OS Independent
Requires-Python: >=3.6
License-File: LICENSE
Requires-Dist: aiohttp
Requires-Dist: requests
